lsinf2172/__init__.py
lsinf2172/dbms.py
lsinf2172/puzzle.py
lsinf2172/resources/Rel-standalone/AUTHORS.txt
lsinf2172/resources/Rel-standalone/CHANGES.txt
lsinf2172/resources/Rel-standalone/LICENSE.txt
lsinf2172/resources/Rel-standalone/README.txt
lsinf2172/resources/Rel-standalone/RelDBMS.jar
lsinf2172/resources/Rel-standalone/RelTest.jar
lsinf2172/resources/Rel-standalone/TODO.txt
lsinf2172/resources/Rel-standalone/commons-codec-1.4.jar
lsinf2172/resources/Rel-standalone/commons-logging-1.1.1.jar
lsinf2172/resources/Rel-standalone/ecj-4.4.2.jar
lsinf2172/resources/Rel-standalone/httpclient-4.1.3.jar
lsinf2172/resources/Rel-standalone/httpclient-cache-4.1.3.jar
lsinf2172/resources/Rel-standalone/httpcore-4.1.4.jar
lsinf2172/resources/Rel-standalone/httpmime-4.1.3.jar
lsinf2172/resources/Rel-standalone/je-7.0.6.jar
lsinf2172/resources/Rel-standalone/junit.jar
lsinf2172/resources/Rel-standalone/rel0000.jar
lsinf2172/resources/Rel-standalone/relclient.jar
lsinf2172/resources/Rel-standalone/relshared.jar
lsinf2172_inginious_utils-1.0rc11.dist-info/DESCRIPTION.rst
lsinf2172_inginious_utils-1.0rc11.dist-info/METADATA
lsinf2172_inginious_utils-1.0rc11.dist-info/RECORD
lsinf2172_inginious_utils-1.0rc11.dist-info/WHEEL
lsinf2172_inginious_utils-1.0rc11.dist-info/metadata.json
lsinf2172_inginious_utils-1.0rc11.dist-info/top_level.txt
