Metadata-Version: 2.0
Name: lsinf2172-inginious-utils
Version: 1.0rc11
Summary: Helper classes to ease the writing of tests on inginious
Home-page: UNKNOWN
Author: X. Gillard
Author-email: xavier.gillard [at] uclouvain.be
License: Apache
Platform: UNKNOWN
Classifier: Development Status :: 3 - Alpha
Classifier: Topic :: Utilities
Classifier: License :: OSI Approved :: Apache Software License
